LICENSE
MANIFEST.in
README.md
setup.cfg
setup.py
pypcappy/__init__.py
pypcappy/packet.py
pypcappy/pcapNgFile.py
pypcappy.egg-info/PKG-INFO
pypcappy.egg-info/SOURCES.txt
pypcappy.egg-info/dependency_links.txt
pypcappy.egg-info/not-zip-safe
pypcappy.egg-info/top_level.txt
pypcappy/blocks/__init__.py
pypcappy/blocks/abstract.py
pypcappy/blocks/custom.py
pypcappy/blocks/enhancedpacket.py
pypcappy/blocks/interfacedescription.py
pypcappy/blocks/sectionheader.py