Metadata-Version: 1.1
Name: pypcappy
Version: 0.0.7
Summary: Pure Python3 PcapNg reader
Home-page: https://github.com/TheBiggerGuy/pypcappy
Author: Guy Taylor
Author-email: thebigguy.co.uk@gmail.com
License: MIT
Keywords: pcap
Platform: UNKNOWN
Classifier: Development Status :: 3 - Alpha
Classifier: License :: OSI Approved :: MIT License
Classifier: Operating System :: OS Independent
Classifier: Programming Language :: Python
Classifier: Programming Language :: Python :: 3.4
Classifier: Programming Language :: Python :: Implementation :: CPython
Classifier: Programming Language :: Python :: Implementation :: PyPy
